[{"timestamp":0.0,"cpu":79.0,"ram":58.0,"disk":50.0,"network":10.0},{"timestamp":100.0,"cpu":59.0,"ram":50.0,"disk":82.0,"network":8.0},{"timestamp":200.0,"cpu":17.0,"ram":6.0,"disk":63.0,"network":8.0},{"timestamp":300.0,"cpu":35.0,"ram":29.0,"disk":81.0,"network":10.0},{"timestamp":400.0,"cpu":70.0,"ram":53.0,"disk":61.0,"network":17.0},{"timestamp":500.0,"cpu":54.0,"ram":41.0,"disk":68.0,"network":8.0},{"timestamp":600.0,"cpu":13.0,"ram":-6.0,"disk":43.0,"network":14.0},{"timestamp":700.0,"cpu":75.0,"ram":69.0,"disk":86.0,"network":9.0},{"timestamp":800.0,"cpu":71.0,"ram":54.0,"disk":57.0,"network":9.0},{"timestamp":900.0,"cpu":27.0,"ram":11.0,"disk":62.0,"network":10.0},{"timestamp":1000.0,"cpu":17.3469140681,"ram":3.8189465422,"disk":65.4906325733,"network":5.7640555853},{"timestamp":1100.0,"cpu":56.9783843224,"ram":41.5235369632,"disk":51.8583928016,"network":13.1324556573}]